{
  "creeps":{
    "melee": {
      "name": "Melee Creep",
      "attribute": "Creeps",
      "range": "Melee",
      "hp": 30,
      "damage": 18,
      "armor": 2,
      "resistance": 1
    },
    "ranged": {
      "name": "Ranged Creep",
      "attribute": "Creeps",
      "range": "Ranged",
      "hp": 26,
      "damage": 14,
      "armor": 1,
      "mana": 4,
      "resistance": 2
    },
    "catapult": {
      "name": "Catapult",
      "attribute": "Creeps",
      "range": "Far",
      "hp": 32,
      "damage": 14,
      "armor": 4,
      "resistance": 6
    }
  },
  "forest":{
    "cent": {
      "name": "Centaur",
      "attribute": "Jungle Creep",
      "range": "Melee",
      "hp": 38,
      "damage": 6,
      "armor": 2,
      "resistance": 3,
      "description": "Centaur Jungle Creep"
     },
    "golem": {
      "name": "Golem",
      "attribute": "Jungle Creep",
      "range": "Melee",
      "hp": 34,
      "damage": 7,
      "armor": 4,
      "resistance": 3,
      "description": "Golem Jungle Creep"
    }
  }
}
